PyCurrency_Converter/PyCurrency.py
PyCurrency_Converter/__init__.py
PyCurrency_Converter-1.0.dist-info/DESCRIPTION.rst
PyCurrency_Converter-1.0.dist-info/METADATA
PyCurrency_Converter-1.0.dist-info/RECORD
PyCurrency_Converter-1.0.dist-info/WHEEL
PyCurrency_Converter-1.0.dist-info/metadata.json
PyCurrency_Converter-1.0.dist-info/top_level.txt
