Metadata-Version: 2.0
Name: PyCurrency-Converter
Version: 1.0
Summary: A python library to convert currency using Google Finance.
Home-page: https://github.com/SiddharthSaxena/PyCurrency-Converter
Author: Siddharth Saxena
Author-email: siddharth.saxena25@gmail.com
License: GNU General Public License v3 (GPLv3)
Download-URL: https://github.com/SiddharthSaxena/PyCurrency-Converter
Keywords: currency converter google
Platform: UNKNOWN
Classifier: Development Status :: 5 - Production/Stable
Classifier: Topic :: Software Development :: Libraries
Classifier: License :: OSI Approved :: GNU General Public License v3 (GPLv3)
Classifier: Programming Language :: Python :: 2
Classifier: Programming Language :: Python :: 2.6
Classifier: Programming Language :: Python :: 2.7
Classifier: Programming Language :: Python :: 3
Classifier: Programming Language :: Python :: 3.2
Classifier: Programming Language :: Python :: 3.3
Classifier: Programming Language :: Python :: 3.4
Classifier: Programming Language :: Python :: 3.5
Requires: B
Requires: e
Requires: a
Requires: u
Requires: t
Requires: i
Requires: f
Requires: u
Requires: l
Requires: S
Requires: o
Requires: u
Requires: p
